mialab/__init__.py
mialab/data/__init__.py
mialab/data/structure.py
mialab/filtering/__init__.py
mialab/filtering/feature_extraction.py
mialab/filtering/postprocessing.py
mialab/filtering/preprocessing.py
mialab/utilities/__init__.py
mialab/utilities/file_access_utilities.py
mialab/utilities/multi_processor.py
mialab/utilities/pipeline_utilities.py
MIALab-0.1.0.dist-info/LICENSE
MIALab-0.1.0.dist-info/METADATA
MIALab-0.1.0.dist-info/WHEEL
MIALab-0.1.0.dist-info/top_level.txt
MIALab-0.1.0.dist-info/RECORD
