Metadata-Version: 2.1
Name: MIALab
Version: 0.1.0
Summary: medical image analysis laboratory
Home-page: https://github.com/ubern-mialab/mialab
Author: Healthcare Imaging A.I.
Author-email: mauricio.reyes@med.unibe.ch
License: Copyright 2017 The MIALab Authors.  All rights reserved.
Keywords: medical image analysis,machine learning,neuro
Classifier: Development Status :: 3 - Alpha
Classifier: Intended Audience :: Developers
Classifier: Intended Audience :: Science/Research
Classifier: License :: OSI Approved :: Apache Software License
Classifier: Natural Language :: English
Classifier: Programming Language :: Python :: 3.8
Classifier: Topic :: Scientific/Engineering :: Image Recognition
Classifier: Topic :: Scientific/Engineering :: Mathematics
Classifier: Topic :: Scientific/Engineering :: Medical Science Apps.
Classifier: Topic :: Software Development :: Libraries :: Python Modules
Classifier: Topic :: Software Development :: Libraries
License-File: LICENSE
Requires-Dist: pymia ==0.3.1
Requires-Dist: scikit-learn >=0.23.2
Requires-Dist: pathos >=0.2.6
